chart_releaser/cli.py
chart_releaser/gitlab_api.py
chart_releaser/handlers.py
chart_releaser/logger.py
chart_releaser/main.py
chart_releaser-1.0.2.dist-info/METADATA
chart_releaser-1.0.2.dist-info/WHEEL
chart_releaser-1.0.2.dist-info/entry_points.txt
chart_releaser-1.0.2.dist-info/RECORD
