Metadata-Version: 2.1
Name: chart_releaser
Version: 1.0.2
Summary: Helm chart releaser tools
License: MIT
Author: Trusikhin Andrei
Author-email: andrei.trusikhin@gmail.com
Requires-Python: >=3.8
Classifier: Intended Audience :: Developers
Classifier: License :: OSI Approved :: MIT License
Classifier: Operating System :: OS Independent
Classifier: Programming Language :: Python :: 3
Classifier: Programming Language :: Python :: 3.8
Classifier: Programming Language :: Python :: 3.9
Classifier: Programming Language :: Python :: 3.10
Classifier: Programming Language :: Python :: 3.11
Classifier: Programming Language :: Python :: 3.12
Classifier: Topic :: Software Development :: Libraries :: Python Modules
Requires-Dist: pyyaml (>=6.0.0,<7.0.0)
Requires-Dist: requests (>=2.26.0,<3.0.0)
Project-URL: Documentation, https://github.com/Onder7994/chart_releaser#readme
Project-URL: Homepage, https://github.com/Onder7994/chart_releaser
Project-URL: Repository, https://github.com/Onder7994/chart_releaser
